{
  "addresses": [
    {
      "apptnrs": [
        "0001", 
        "0101"
      ], 
      "hnrlbls": [
        "10"
      ], 
      "housenumber": "10", 
      "lat": 51.216652443975, 
      "lon": 5.268021951128, 
      "municipality": "Lommel", 
      "pcode": "3920", 
      "source": "manueleAanduidingVanGebouw", 
      "street": "Edward Anseelestraat"
    }, 
    {
      "busnrs": [
        "0001"
      ], 
      "hnrlbls": [
        "11"
      ], 
      "housenumber": "11", 
      "lat": 51.215808729389, 
      "lon": 5.266970568503, 
      "municipality": "Lommel", 
      "pcode": "3920", 
      "source": "manueleAanduidingVanGebouw", 
      "street": "Edward Anseelestraat"
    }, 
    {
      "hnrlbls": [
        "15"
      ], 
      "housenumber": "15", 
      "lat": 51.216524167204, 
      "lon": 5.266604207434, 
      "municipality": "Lommel", 
      "pcode": "3920", 
      "source": "manueleAanduidingVanGebouw", 
      "street": "Edward Anseelestraat"
    }, 
    {
      "hnrlbls": [
        "16"
      ], 
      "housenumber": "16", 
      "lat": 51.217132301843, 
      "lon": 5.26712118099, 
      "municipality": "Lommel", 
      "pcode": "3920", 
      "source": "manueleAanduidingVanPerceel", 
      "street": "Edward Anseelestraat"
    }, 
    {
      "hnrlbls": [
        "17"
      ], 
      "housenumber": "17", 
      "lat": 51.216910850819, 
      "lon": 5.266039707182, 
      "municipality": "Lommel", 
      "pcode": "3920", 
      "source": "manueleAanduidingVanGebouw", 
      "street": "Edward Anseelestraat"
    }, 
    {
      "hnrlbls": [
        "18"
      ], 
      "housenumber": "18", 
      "lat": 51.217307031677, 
      "lon": 5.266993440811, 
      "municipality": "Lommel", 
      "pcode": "3920", 
      "source": "manueleAanduidingVanPerceel", 
      "street": "Edward Anseelestraat"
    }, 
    {
      "hnrlbls": [
        "20"
      ], 
      "housenumber": "20", 
      "lat": 51.217708838165, 
      "lon": 5.266686579614, 
      "municipality": "Lommel", 
      "pcode": "3920", 
      "source": "manueleAanduidingVanGebouw", 
      "street": "Edward Anseelestraat"
    }, 
    {
      "hnrlbls": [
        "21"
      ], 
      "housenumber": "21", 
      "lat": 51.217422066547, 
      "lon": 5.26541118082, 
      "municipality": "Lommel", 
      "pcode": "3920", 
      "source": "manueleAanduidingVanGebouw", 
      "street": "Edward Anseelestraat"
    }, 
    {
      "hnrlbls": [
        "24"
      ], 
      "housenumber": "24", 
      "lat": 51.217848470354, 
      "lon": 5.267368011581, 
      "municipality": "Lommel", 
      "pcode": "3920", 
      "source": "manueleAanduidingVanPerceel", 
      "street": "Edward Anseelestraat"
    }, 
    {
      "apptnrs": [
        "0201"
      ], 
      "busnrs": [
        "0202", 
        "0203"
      ], 
      "hnrlbls": [
        "26"
      ], 
      "housenumber": "26", 
      "lat": 51.217923277643, 
      "lon": 5.267755487156, 
      "municipality": "Lommel", 
      "pcode": "3920", 
      "source": "manueleAanduidingVanPerceel", 
      "street": "Edward Anseelestraat"
    }, 
    {
      "hnrlbls": [
        "6"
      ], 
      "housenumber": "6", 
      "lat": 51.215925706443, 
      "lon": 5.268455057291, 
      "municipality": "Lommel", 
      "pcode": "3920", 
      "source": "afgeleidVanGebouw", 
      "street": "Edward Anseelestraat"
    }
  ]
}