{
  "addresses": [
    {
      "apptnrs": [
        "1", 
        "2", 
        "3", 
        "4"
      ], 
      "hnrlbls": [
        "1"
      ], 
      "housenumber": "1", 
      "lat": 51.246668380069, 
      "lon": 5.438386775011, 
      "municipality": "Pelt", 
      "pcode": "3910", 
      "source": "afgeleidVanGebouw", 
      "street": "Regenboogplein"
    }, 
    {
      "hnrlbls": [
        "10"
      ], 
      "housenumber": "10", 
      "lat": 51.247392666092, 
      "lon": 5.438513268115, 
      "municipality": "Pelt", 
      "pcode": "3910", 
      "source": "manueleAanduidingVanPerceel", 
      "street": "Regenboogplein"
    }, 
    {
      "hnrlbls": [
        "12"
      ], 
      "housenumber": "12", 
      "lat": 51.247398114824, 
      "lon": 5.438437625116, 
      "municipality": "Pelt", 
      "pcode": "3910", 
      "source": "manueleAanduidingVanPerceel", 
      "street": "Regenboogplein"
    }, 
    {
      "hnrlbls": [
        "14"
      ], 
      "housenumber": "14", 
      "lat": 51.2474036827, 
      "lon": 5.438348807762, 
      "municipality": "Pelt", 
      "pcode": "3910", 
      "source": "manueleAanduidingVanPerceel", 
      "street": "Regenboogplein"
    }, 
    {
      "hnrlbls": [
        "16"
      ], 
      "housenumber": "16", 
      "lat": 51.247411519859, 
      "lon": 5.43826749042, 
      "municipality": "Pelt", 
      "pcode": "3910", 
      "source": "manueleAanduidingVanPerceel", 
      "street": "Regenboogplein"
    }, 
    {
      "hnrlbls": [
        "18"
      ], 
      "housenumber": "18", 
      "lat": 51.24741595552, 
      "lon": 5.438174636607, 
      "municipality": "Pelt", 
      "pcode": "3910", 
      "source": "manueleAanduidingVanPerceel", 
      "street": "Regenboogplein"
    }, 
    {
      "hnrlbls": [
        "2"
      ], 
      "housenumber": "2", 
      "lat": 51.2473687574, 
      "lon": 5.438920205297, 
      "municipality": "Pelt", 
      "pcode": "3910", 
      "source": "manueleAanduidingVanPerceel", 
      "street": "Regenboogplein"
    }, 
    {
      "hnrlbls": [
        "20"
      ], 
      "housenumber": "20", 
      "lat": 51.247422743365, 
      "lon": 5.438080118043, 
      "municipality": "Pelt", 
      "pcode": "3910", 
      "source": "manueleAanduidingVanPerceel", 
      "street": "Regenboogplein"
    }, 
    {
      "apptnrs": [
        "1", 
        "2", 
        "3", 
        "4"
      ], 
      "hnrlbls": [
        "3"
      ], 
      "housenumber": "3", 
      "lat": 51.246693472514, 
      "lon": 5.438087291048, 
      "municipality": "Pelt", 
      "pcode": "3910", 
      "source": "afgeleidVanGebouw", 
      "street": "Regenboogplein"
    }, 
    {
      "hnrlbls": [
        "4"
      ], 
      "housenumber": "4", 
      "lat": 51.247373227274, 
      "lon": 5.438823628453, 
      "municipality": "Pelt", 
      "pcode": "3910", 
      "source": "manueleAanduidingVanPerceel", 
      "street": "Regenboogplein"
    }, 
    {
      "apptnrs": [
        "1", 
        "2", 
        "3", 
        "4", 
        "5"
      ], 
      "hnrlbls": [
        "5"
      ], 
      "housenumber": "5", 
      "lat": 51.246650927693, 
      "lon": 5.437772074639, 
      "municipality": "Pelt", 
      "pcode": "3910", 
      "source": "afgeleidVanGebouw", 
      "street": "Regenboogplein"
    }, 
    {
      "hnrlbls": [
        "6"
      ], 
      "housenumber": "6", 
      "lat": 51.24738005063, 
      "lon": 5.43872524369, 
      "municipality": "Pelt", 
      "pcode": "3910", 
      "source": "manueleAanduidingVanPerceel", 
      "street": "Regenboogplein"
    }, 
    {
      "apptnrs": [
        "1", 
        "2", 
        "3", 
        "4"
      ], 
      "hnrlbls": [
        "7"
      ], 
      "housenumber": "7", 
      "lat": 51.246892107536, 
      "lon": 5.437792077135, 
      "municipality": "Pelt", 
      "pcode": "3910", 
      "source": "manueleAanduidingVanGebouw", 
      "street": "Regenboogplein"
    }, 
    {
      "hnrlbls": [
        "8"
      ], 
      "housenumber": "8", 
      "lat": 51.247386942586, 
      "lon": 5.438619269338, 
      "municipality": "Pelt", 
      "pcode": "3910", 
      "source": "manueleAanduidingVanPerceel", 
      "street": "Regenboogplein"
    }, 
    {
      "apptnrs": [
        "1", 
        "2", 
        "3", 
        "4"
      ], 
      "hnrlbls": [
        "9"
      ], 
      "housenumber": "9", 
      "lat": 51.246910772841, 
      "lon": 5.437557039561, 
      "municipality": "Pelt", 
      "pcode": "3910", 
      "source": "manueleAanduidingVanGebouw", 
      "street": "Regenboogplein"
    }
  ]
}