{
  "addresses": [
    {
      "busnrs": [
        "101", 
        "102", 
        "201", 
        "202"
      ], 
      "hnrlbls": [
        "1-8"
      ], 
      "housenumber": "1", 
      "lat": 51.059324425956, 
      "lon": 4.364380677736, 
      "municipality": "Willebroek", 
      "pcode": "2830", 
      "source": "afgeleidVanGebouw", 
      "street": "Oostdijk"
    }, 
    {
      "hnrlbls": [
        "101"
      ], 
      "housenumber": "101", 
      "lat": 51.054348662068, 
      "lon": 4.363441038341, 
      "municipality": "Willebroek", 
      "pcode": "2830", 
      "source": "afgeleidVanGebouw", 
      "street": "Oostdijk"
    }, 
    {
      "hnrlbls": [
        "102"
      ], 
      "housenumber": "102", 
      "lat": 51.054138321292, 
      "lon": 4.363448903356, 
      "municipality": "Willebroek", 
      "pcode": "2830", 
      "source": "afgeleidVanGebouw", 
      "street": "Oostdijk"
    }, 
    {
      "hnrlbls": [
        "103"
      ], 
      "housenumber": "103", 
      "lat": 51.053956208958, 
      "lon": 4.363539343766, 
      "municipality": "Willebroek", 
      "pcode": "2830", 
      "source": "afgeleidVanGebouw", 
      "street": "Oostdijk"
    }, 
    {
      "hnrlbls": [
        "104"
      ], 
      "housenumber": "104", 
      "lat": 51.053784162736, 
      "lon": 4.363592273023, 
      "municipality": "Willebroek", 
      "pcode": "2830", 
      "source": "afgeleidVanGebouw", 
      "street": "Oostdijk"
    }, 
    {
      "hnrlbls": [
        "105"
      ], 
      "housenumber": "105", 
      "lat": 51.053741645902, 
      "lon": 4.363614383419, 
      "municipality": "Willebroek", 
      "pcode": "2830", 
      "source": "afgeleidVanGebouw", 
      "street": "Oostdijk"
    }, 
    {
      "hnrlbls": [
        "106"
      ], 
      "housenumber": "106", 
      "lat": 51.053607711204, 
      "lon": 4.363626661561, 
      "municipality": "Willebroek", 
      "pcode": "2830", 
      "source": "afgeleidVanGebouw", 
      "street": "Oostdijk"
    }, 
    {
      "hnrlbls": [
        "107"
      ], 
      "housenumber": "107", 
      "lat": 51.05348950991, 
      "lon": 4.363713386182, 
      "municipality": "Willebroek", 
      "pcode": "2830", 
      "source": "afgeleidVanGebouw", 
      "street": "Oostdijk"
    }, 
    {
      "hnrlbls": [
        "109"
      ], 
      "housenumber": "109", 
      "lat": 51.053116833557, 
      "lon": 4.363851619217, 
      "municipality": "Willebroek", 
      "pcode": "2830", 
      "source": "afgeleidVanGebouw", 
      "street": "Oostdijk"
    }, 
    {
      "hnrlbls": [
        "110"
      ], 
      "housenumber": "110", 
      "lat": 51.052188356719, 
      "lon": 4.363601125018, 
      "municipality": "Willebroek", 
      "pcode": "2830", 
      "source": "manueleAanduidingVanPerceel", 
      "street": "Oostdijk"
    }, 
    {
      "hnrlbls": [
        "12"
      ], 
      "housenumber": "12", 
      "lat": 51.050938799154, 
      "lon": 4.363482732698, 
      "municipality": "Willebroek", 
      "pcode": "2830", 
      "source": "afgeleidVanGebouw", 
      "street": "Oostdijk"
    }, 
    {
      "hnrlbls": [
        "2"
      ], 
      "housenumber": "2", 
      "lat": 51.050318462798, 
      "lon": 4.363252476459, 
      "municipality": "Willebroek", 
      "pcode": "2830", 
      "source": "afgeleidVanStraat", 
      "street": "Oostdijk"
    }, 
    {
      "busnrs": [
        "1", 
        "101", 
        "102", 
        "2", 
        "201", 
        "202", 
        "204", 
        "21"
      ], 
      "hnrlbls": [
        "1-8"
      ], 
      "housenumber": "3", 
      "lat": 51.059324425956, 
      "lon": 4.364380677736, 
      "municipality": "Willebroek", 
      "pcode": "2830", 
      "source": "afgeleidVanGebouw", 
      "street": "Oostdijk"
    }, 
    {
      "busnrs": [
        "1", 
        "101", 
        "102", 
        "2", 
        "201"
      ], 
      "hnrlbls": [
        "1-8"
      ], 
      "housenumber": "5", 
      "lat": 51.059324425956, 
      "lon": 4.364380677736, 
      "municipality": "Willebroek", 
      "pcode": "2830", 
      "source": "afgeleidVanGebouw", 
      "street": "Oostdijk"
    }, 
    {
      "hnrlbls": [
        "55"
      ], 
      "housenumber": "55", 
      "lat": 51.057094080639, 
      "lon": 4.363964511072, 
      "municipality": "Willebroek", 
      "pcode": "2830", 
      "source": "geinterpoleerdObvNevenliggendeHuisnummersGebouw", 
      "street": "Oostdijk"
    }, 
    {
      "hnrlbls": [
        "72-74"
      ], 
      "housenumber": "72", 
      "lat": 51.055753729682, 
      "lon": 4.363637440547, 
      "municipality": "Willebroek", 
      "pcode": "2830", 
      "source": "afgeleidVanPerceelGrb", 
      "street": "Oostdijk"
    }, 
    {
      "busnrs": [
        "101", 
        "102", 
        "2", 
        "201", 
        "202"
      ], 
      "hnrlbls": [
        "72-74"
      ], 
      "housenumber": "74", 
      "lat": 51.055753729682, 
      "lon": 4.363637440547, 
      "municipality": "Willebroek", 
      "pcode": "2830", 
      "source": "afgeleidVanPerceelGrb", 
      "street": "Oostdijk"
    }, 
    {
      "hnrlbls": [
        "96"
      ], 
      "housenumber": "96", 
      "lat": 51.054959734067, 
      "lon": 4.363551227327, 
      "municipality": "Willebroek", 
      "pcode": "2830", 
      "source": "manueleAanduidingVanIngangVanGebouw", 
      "street": "Oostdijk"
    }, 
    {
      "busnrs": [
        "1", 
        "101", 
        "102", 
        "103", 
        "11", 
        "2", 
        "201", 
        "202", 
        "203"
      ], 
      "hnrlbls": [
        "97"
      ], 
      "housenumber": "97", 
      "lat": 51.054869299194, 
      "lon": 4.363391923957, 
      "municipality": "Willebroek", 
      "pcode": "2830", 
      "source": "manueleAanduidingVanIngangVanGebouw", 
      "street": "Oostdijk"
    }, 
    {
      "busnrs": [
        "1", 
        "101", 
        "2", 
        "201"
      ], 
      "hnrlbls": [
        "98"
      ], 
      "housenumber": "98", 
      "lat": 51.054762779659, 
      "lon": 4.363374962252, 
      "municipality": "Willebroek", 
      "pcode": "2830", 
      "source": "manueleAanduidingVanIngangVanGebouw", 
      "street": "Oostdijk"
    }, 
    {
      "busnrs": [
        "1", 
        "101", 
        "2", 
        "201", 
        "202"
      ], 
      "hnrlbls": [
        "99"
      ], 
      "housenumber": "99", 
      "lat": 51.054640350171, 
      "lon": 4.363369697413, 
      "municipality": "Willebroek", 
      "pcode": "2830", 
      "source": "manueleAanduidingVanIngangVanGebouw", 
      "street": "Oostdijk"
    }
  ]
}