{
  "addresses": [
    {
      "hnrlbls": [
        "1"
      ], 
      "housenumber": "1", 
      "lat": 50.993684652627, 
      "lon": 5.068327560385, 
      "municipality": "Diest", 
      "pcode": "3290", 
      "source": "afgeleidVanGebouw", 
      "street": "Ten Aerde"
    }, 
    {
      "busnrs": [
        "1A", 
        "1B", 
        "2"
      ], 
      "hnrlbls": [
        "10-12B"
      ], 
      "housenumber": "10", 
      "lat": 50.993294550377, 
      "lon": 5.068139117509, 
      "municipality": "Diest", 
      "pcode": "3290", 
      "source": "afgeleidVanGebouw", 
      "street": "Ten Aerde"
    }, 
    {
      "busnrs": [
        "1"
      ], 
      "hnrlbls": [
        "10-12B"
      ], 
      "housenumber": "10A", 
      "lat": 50.993294550377, 
      "lon": 5.068139117509, 
      "municipality": "Diest", 
      "pcode": "3290", 
      "source": "afgeleidVanGebouw", 
      "street": "Ten Aerde"
    }, 
    {
      "busnrs": [
        "1"
      ], 
      "hnrlbls": [
        "10-12B"
      ], 
      "housenumber": "10B", 
      "lat": 50.993294550377, 
      "lon": 5.068139117509, 
      "municipality": "Diest", 
      "pcode": "3290", 
      "source": "afgeleidVanGebouw", 
      "street": "Ten Aerde"
    }, 
    {
      "hnrlbls": [
        "11"
      ], 
      "housenumber": "11", 
      "lat": 50.993463220783, 
      "lon": 5.067877688076, 
      "municipality": "Diest", 
      "pcode": "3290", 
      "source": "afgeleidVanGebouw", 
      "street": "Ten Aerde"
    }, 
    {
      "busnrs": [
        "1A", 
        "1B", 
        "2"
      ], 
      "hnrlbls": [
        "10-12B"
      ], 
      "housenumber": "12", 
      "lat": 50.993294550377, 
      "lon": 5.068139117509, 
      "municipality": "Diest", 
      "pcode": "3290", 
      "source": "afgeleidVanGebouw", 
      "street": "Ten Aerde"
    }, 
    {
      "busnrs": [
        "1"
      ], 
      "hnrlbls": [
        "10-12B"
      ], 
      "housenumber": "12A", 
      "lat": 50.993294550377, 
      "lon": 5.068139117509, 
      "municipality": "Diest", 
      "pcode": "3290", 
      "source": "afgeleidVanGebouw", 
      "street": "Ten Aerde"
    }, 
    {
      "busnrs": [
        "1"
      ], 
      "hnrlbls": [
        "10-12B"
      ], 
      "housenumber": "12B", 
      "lat": 50.993294550377, 
      "lon": 5.068139117509, 
      "municipality": "Diest", 
      "pcode": "3290", 
      "source": "afgeleidVanGebouw", 
      "street": "Ten Aerde"
    }, 
    {
      "hnrlbls": [
        "13"
      ], 
      "housenumber": "13", 
      "lat": 50.993406800943, 
      "lon": 5.067811463567, 
      "municipality": "Diest", 
      "pcode": "3290", 
      "source": "afgeleidVanGebouw", 
      "street": "Ten Aerde"
    }, 
    {
      "busnrs": [
        "1", 
        "2"
      ], 
      "hnrlbls": [
        "15A-15B"
      ], 
      "housenumber": "15A", 
      "lat": 50.993244018975, 
      "lon": 5.067506054923, 
      "municipality": "Diest", 
      "pcode": "3290", 
      "source": "afgeleidVanGebouw", 
      "street": "Ten Aerde"
    }, 
    {
      "busnrs": [
        "1", 
        "2"
      ], 
      "hnrlbls": [
        "15A-15B"
      ], 
      "housenumber": "15B", 
      "lat": 50.993244018975, 
      "lon": 5.067506054923, 
      "municipality": "Diest", 
      "pcode": "3290", 
      "source": "afgeleidVanGebouw", 
      "street": "Ten Aerde"
    }, 
    {
      "hnrlbls": [
        "2"
      ], 
      "housenumber": "2", 
      "lat": 50.993692407451, 
      "lon": 5.068761421565, 
      "municipality": "Diest", 
      "pcode": "3290", 
      "source": "afgeleidVanGebouw", 
      "street": "Ten Aerde"
    }, 
    {
      "hnrlbls": [
        "3"
      ], 
      "housenumber": "3", 
      "lat": 50.993636719698, 
      "lon": 5.0682400951, 
      "municipality": "Diest", 
      "pcode": "3290", 
      "source": "afgeleidVanGebouw", 
      "street": "Ten Aerde"
    }, 
    {
      "hnrlbls": [
        "4"
      ], 
      "housenumber": "4", 
      "lat": 50.993619615165, 
      "lon": 5.068621734192, 
      "municipality": "Diest", 
      "pcode": "3290", 
      "source": "manueleAanduidingVanGebouw", 
      "street": "Ten Aerde"
    }, 
    {
      "hnrlbls": [
        "5"
      ], 
      "housenumber": "5", 
      "lat": 50.99360535386, 
      "lon": 5.068133077691, 
      "municipality": "Diest", 
      "pcode": "3290", 
      "source": "afgeleidVanGebouw", 
      "street": "Ten Aerde"
    }, 
    {
      "hnrlbls": [
        "6"
      ], 
      "housenumber": "6", 
      "lat": 50.993547967509, 
      "lon": 5.06851625108, 
      "municipality": "Diest", 
      "pcode": "3290", 
      "source": "manueleAanduidingVanGebouw", 
      "street": "Ten Aerde"
    }, 
    {
      "hnrlbls": [
        "7"
      ], 
      "housenumber": "7", 
      "lat": 50.993542250255, 
      "lon": 5.068057066589, 
      "municipality": "Diest", 
      "pcode": "3290", 
      "source": "manueleAanduidingVanGebouw", 
      "street": "Ten Aerde"
    }, 
    {
      "hnrlbls": [
        "8"
      ], 
      "housenumber": "8", 
      "lat": 50.993486491402, 
      "lon": 5.06839339965, 
      "municipality": "Diest", 
      "pcode": "3290", 
      "source": "afgeleidVanGebouw", 
      "street": "Ten Aerde"
    }, 
    {
      "hnrlbls": [
        "9"
      ], 
      "housenumber": "9", 
      "lat": 50.993492693293, 
      "lon": 5.067985673817, 
      "municipality": "Diest", 
      "pcode": "3290", 
      "source": "manueleAanduidingVanGebouw", 
      "street": "Ten Aerde"
    }
  ]
}