{
  "addresses": [
    {
      "hnrlbls": [
        "46"
      ], 
      "housenumber": "46", 
      "lat": 50.954857791635, 
      "lon": 3.157696814697, 
      "municipality": "Roeselare", 
      "pcode": "8800", 
      "source": "manueleAanduidingVanGebouw", 
      "street": "Bloemkoolstraat"
    }, 
    {
      "hnrlbls": [
        "48"
      ], 
      "housenumber": "48", 
      "lat": 50.954814287048, 
      "lon": 3.157741351148, 
      "municipality": "Roeselare", 
      "pcode": "8800", 
      "source": "manueleAanduidingVanGebouw", 
      "street": "Bloemkoolstraat"
    }, 
    {
      "hnrlbls": [
        "50"
      ], 
      "housenumber": "50", 
      "lat": 50.954738118845, 
      "lon": 3.157739473842, 
      "municipality": "Roeselare", 
      "pcode": "8800", 
      "source": "manueleAanduidingVanGebouw", 
      "street": "Bloemkoolstraat"
    }, 
    {
      "hnrlbls": [
        "67"
      ], 
      "housenumber": "67", 
      "lat": 50.955260182843, 
      "lon": 3.157738525509, 
      "municipality": "Roeselare", 
      "pcode": "8800", 
      "source": "manueleAanduidingVanGebouw", 
      "street": "Bloemkoolstraat"
    }
  ]
}