{
  "addresses": [
    {
      "hnrlbls": [
        "1"
      ], 
      "housenumber": "1", 
      "lat": 51.335181845401, 
      "lon": 4.956927060141, 
      "municipality": "Turnhout", 
      "pcode": "2300", 
      "source": "afgeleidVanPerceelGrb", 
      "street": "Wulpenplein"
    }, 
    {
      "hnrlbls": [
        "17"
      ], 
      "housenumber": "17", 
      "lat": 51.334426364164, 
      "lon": 4.957166014068, 
      "municipality": "Turnhout", 
      "pcode": "2300", 
      "source": "afgeleidVanPerceelGrb", 
      "street": "Wulpenplein"
    }, 
    {
      "hnrlbls": [
        "18"
      ], 
      "housenumber": "18", 
      "lat": 51.334556777146, 
      "lon": 4.956968362351, 
      "municipality": "Turnhout", 
      "pcode": "2300", 
      "source": "afgeleidVanGebouw", 
      "street": "Wulpenplein"
    }, 
    {
      "hnrlbls": [
        "19"
      ], 
      "housenumber": "19", 
      "lat": 51.334542989016, 
      "lon": 4.956812791342, 
      "municipality": "Turnhout", 
      "pcode": "2300", 
      "source": "afgeleidVanGebouw", 
      "street": "Wulpenplein"
    }, 
    {
      "hnrlbls": [
        "2"
      ], 
      "housenumber": "2", 
      "lat": 51.335144373513, 
      "lon": 4.957033771893, 
      "municipality": "Turnhout", 
      "pcode": "2300", 
      "source": "afgeleidVanPerceelGrb", 
      "street": "Wulpenplein"
    }, 
    {
      "hnrlbls": [
        "20"
      ], 
      "housenumber": "20", 
      "lat": 51.334545012699, 
      "lon": 4.956676791271, 
      "municipality": "Turnhout", 
      "pcode": "2300", 
      "source": "afgeleidVanGebouw", 
      "street": "Wulpenplein"
    }, 
    {
      "hnrlbls": [
        "21"
      ], 
      "housenumber": "21", 
      "lat": 51.334543077246, 
      "lon": 4.956523522658, 
      "municipality": "Turnhout", 
      "pcode": "2300", 
      "source": "afgeleidVanGebouw", 
      "street": "Wulpenplein"
    }, 
    {
      "hnrlbls": [
        "3"
      ], 
      "housenumber": "3", 
      "lat": 51.335109875989, 
      "lon": 4.957120719698, 
      "municipality": "Turnhout", 
      "pcode": "2300", 
      "source": "afgeleidVanPerceelGrb", 
      "street": "Wulpenplein"
    }, 
    {
      "hnrlbls": [
        "4"
      ], 
      "housenumber": "4", 
      "lat": 51.335075446188, 
      "lon": 4.957230195951, 
      "municipality": "Turnhout", 
      "pcode": "2300", 
      "source": "afgeleidVanPerceelGrb", 
      "street": "Wulpenplein"
    }
  ]
}