{
  "addresses": [
    {
      "hnrlbls": [
        "1"
      ], 
      "housenumber": "1", 
      "lat": 51.073609693664, 
      "lon": 3.71340436007, 
      "municipality": "Gent", 
      "pcode": "9000", 
      "source": "manueleAanduidingVanGebouw", 
      "street": "Egelantierstraat"
    }, 
    {
      "hnrlbls": [
        "2"
      ], 
      "housenumber": "2", 
      "lat": 51.073582106713, 
      "lon": 3.713487076888, 
      "municipality": "Gent", 
      "pcode": "9000", 
      "source": "manueleAanduidingVanGebouw", 
      "street": "Egelantierstraat"
    }, 
    {
      "hnrlbls": [
        "3"
      ], 
      "housenumber": "3", 
      "lat": 51.073542417321, 
      "lon": 3.713591936809, 
      "municipality": "Gent", 
      "pcode": "9000", 
      "source": "manueleAanduidingVanGebouw", 
      "street": "Egelantierstraat"
    }, 
    {
      "hnrlbls": [
        "4"
      ], 
      "housenumber": "4", 
      "lat": 51.07351320755, 
      "lon": 3.713673819974, 
      "municipality": "Gent", 
      "pcode": "9000", 
      "source": "manueleAanduidingVanGebouw", 
      "street": "Egelantierstraat"
    }
  ]
}