{
  "addresses": [
    {
      "hnrlbls": [
        "8-10"
      ], 
      "housenumber": "10", 
      "lat": 51.138527581501, 
      "lon": 5.577892777786, 
      "municipality": "Bree", 
      "pcode": "3960", 
      "source": "afgeleidVanGebouw", 
      "street": "Galgenstraat"
    }, 
    {
      "hnrlbls": [
        "11"
      ], 
      "housenumber": "11", 
      "lat": 51.138130602694, 
      "lon": 5.578163290107, 
      "municipality": "Bree", 
      "pcode": "3960", 
      "source": "afgeleidVanPerceelGrb", 
      "street": "Galgenstraat"
    }, 
    {
      "hnrlbls": [
        "12"
      ], 
      "housenumber": "12", 
      "lat": 51.137806824236, 
      "lon": 5.577344103478, 
      "municipality": "Bree", 
      "pcode": "3960", 
      "source": "afgeleidVanGebouw", 
      "street": "Galgenstraat"
    }, 
    {
      "hnrlbls": [
        "8-10"
      ], 
      "housenumber": "8", 
      "lat": 51.138527581501, 
      "lon": 5.577892777786, 
      "municipality": "Bree", 
      "pcode": "3960", 
      "source": "afgeleidVanGebouw", 
      "street": "Galgenstraat"
    }
  ]
}