{
  "addresses": [
    {
      "hnrlbls": [
        "1"
      ], 
      "housenumber": "1", 
      "lat": 50.850596994128, 
      "lon": 3.350252418008, 
      "municipality": "Deerlijk", 
      "pcode": "8540", 
      "source": "manueleAanduidingVanLot", 
      "street": "Weegbreestraat"
    }, 
    {
      "hnrlbls": [
        "10"
      ], 
      "housenumber": "10", 
      "lat": 50.849994317168, 
      "lon": 3.350132257142, 
      "municipality": "Deerlijk", 
      "pcode": "8540", 
      "source": "manueleAanduidingVanLot", 
      "street": "Weegbreestraat"
    }, 
    {
      "hnrlbls": [
        "12"
      ], 
      "housenumber": "12", 
      "lat": 50.849904934237, 
      "lon": 3.349985075711, 
      "municipality": "Deerlijk", 
      "pcode": "8540", 
      "source": "manueleAanduidingVanLot", 
      "street": "Weegbreestraat"
    }, 
    {
      "hnrlbls": [
        "14"
      ], 
      "housenumber": "14", 
      "lat": 50.849866646931, 
      "lon": 3.349924269959, 
      "municipality": "Deerlijk", 
      "pcode": "8540", 
      "source": "manueleAanduidingVanLot", 
      "street": "Weegbreestraat"
    }, 
    {
      "hnrlbls": [
        "16"
      ], 
      "housenumber": "16", 
      "lat": 50.849836013612, 
      "lon": 3.349875227858, 
      "municipality": "Deerlijk", 
      "pcode": "8540", 
      "source": "manueleAanduidingVanLot", 
      "street": "Weegbreestraat"
    }, 
    {
      "hnrlbls": [
        "18"
      ], 
      "housenumber": "18", 
      "lat": 50.84980658691, 
      "lon": 3.349820195005, 
      "municipality": "Deerlijk", 
      "pcode": "8540", 
      "source": "manueleAanduidingVanLot", 
      "street": "Weegbreestraat"
    }, 
    {
      "hnrlbls": [
        "2"
      ], 
      "housenumber": "2", 
      "lat": 50.850161653269, 
      "lon": 3.350414939698, 
      "municipality": "Deerlijk", 
      "pcode": "8540", 
      "source": "manueleAanduidingVanLot", 
      "street": "Weegbreestraat"
    }, 
    {
      "hnrlbls": [
        "20"
      ], 
      "housenumber": "20", 
      "lat": 50.849774643357, 
      "lon": 3.349765216747, 
      "municipality": "Deerlijk", 
      "pcode": "8540", 
      "source": "manueleAanduidingVanLot", 
      "street": "Weegbreestraat"
    }, 
    {
      "hnrlbls": [
        "22"
      ], 
      "housenumber": "22", 
      "lat": 50.84974392367, 
      "lon": 3.349706235602, 
      "municipality": "Deerlijk", 
      "pcode": "8540", 
      "source": "manueleAanduidingVanLot", 
      "street": "Weegbreestraat"
    }, 
    {
      "hnrlbls": [
        "24"
      ], 
      "housenumber": "24", 
      "lat": 50.849592221987, 
      "lon": 3.349484853925, 
      "municipality": "Deerlijk", 
      "pcode": "8540", 
      "source": "manueleAanduidingVanLot", 
      "street": "Weegbreestraat"
    }, 
    {
      "hnrlbls": [
        "26"
      ], 
      "housenumber": "26", 
      "lat": 50.849519681041, 
      "lon": 3.349392979911, 
      "municipality": "Deerlijk", 
      "pcode": "8540", 
      "source": "manueleAanduidingVanLot", 
      "street": "Weegbreestraat"
    }, 
    {
      "hnrlbls": [
        "28"
      ], 
      "housenumber": "28", 
      "lat": 50.84947368755, 
      "lon": 3.349314448254, 
      "municipality": "Deerlijk", 
      "pcode": "8540", 
      "source": "manueleAanduidingVanLot", 
      "street": "Weegbreestraat"
    }, 
    {
      "hnrlbls": [
        "3"
      ], 
      "housenumber": "3", 
      "lat": 50.850510491444, 
      "lon": 3.35029206806, 
      "municipality": "Deerlijk", 
      "pcode": "8540", 
      "source": "manueleAanduidingVanLot", 
      "street": "Weegbreestraat"
    }, 
    {
      "hnrlbls": [
        "30"
      ], 
      "housenumber": "30", 
      "lat": 50.849423936036, 
      "lon": 3.349237986417, 
      "municipality": "Deerlijk", 
      "pcode": "8540", 
      "source": "manueleAanduidingVanLot", 
      "street": "Weegbreestraat"
    }, 
    {
      "hnrlbls": [
        "32"
      ], 
      "housenumber": "32", 
      "lat": 50.849375408346, 
      "lon": 3.349157521796, 
      "municipality": "Deerlijk", 
      "pcode": "8540", 
      "source": "manueleAanduidingVanLot", 
      "street": "Weegbreestraat"
    }, 
    {
      "hnrlbls": [
        "34"
      ], 
      "housenumber": "34", 
      "lat": 50.849329397425, 
      "lon": 3.349077002778, 
      "municipality": "Deerlijk", 
      "pcode": "8540", 
      "source": "manueleAanduidingVanLot", 
      "street": "Weegbreestraat"
    }, 
    {
      "hnrlbls": [
        "36"
      ], 
      "housenumber": "36", 
      "lat": 50.849283351903, 
      "lon": 3.34899250826, 
      "municipality": "Deerlijk", 
      "pcode": "8540", 
      "source": "manueleAanduidingVanLot", 
      "street": "Weegbreestraat"
    }, 
    {
      "hnrlbls": [
        "38"
      ], 
      "housenumber": "38", 
      "lat": 50.849234634031, 
      "lon": 3.348890178036, 
      "municipality": "Deerlijk", 
      "pcode": "8540", 
      "source": "manueleAanduidingVanLot", 
      "street": "Weegbreestraat"
    }, 
    {
      "hnrlbls": [
        "4"
      ], 
      "housenumber": "4", 
      "lat": 50.850105541422, 
      "lon": 3.35033066036, 
      "municipality": "Deerlijk", 
      "pcode": "8540", 
      "source": "manueleAanduidingVanLot", 
      "street": "Weegbreestraat"
    }, 
    {
      "hnrlbls": [
        "5"
      ], 
      "housenumber": "5", 
      "lat": 50.850431573718, 
      "lon": 3.350335530231, 
      "municipality": "Deerlijk", 
      "pcode": "8540", 
      "source": "manueleAanduidingVanLot", 
      "street": "Weegbreestraat"
    }, 
    {
      "hnrlbls": [
        "6"
      ], 
      "housenumber": "6", 
      "lat": 50.850071012284, 
      "lon": 3.350267784455, 
      "municipality": "Deerlijk", 
      "pcode": "8540", 
      "source": "manueleAanduidingVanLot", 
      "street": "Weegbreestraat"
    }, 
    {
      "hnrlbls": [
        "7"
      ], 
      "housenumber": "7", 
      "lat": 50.850357620628, 
      "lon": 3.350370931766, 
      "municipality": "Deerlijk", 
      "pcode": "8540", 
      "source": "manueleAanduidingVanLot", 
      "street": "Weegbreestraat"
    }, 
    {
      "hnrlbls": [
        "8"
      ], 
      "housenumber": "8", 
      "lat": 50.850035190197, 
      "lon": 3.35020096017, 
      "municipality": "Deerlijk", 
      "pcode": "8540", 
      "source": "manueleAanduidingVanLot", 
      "street": "Weegbreestraat"
    }
  ]
}